rest_filter/__init__.py
rest_filter/encoder/__init__.py
rest_filter/encoder/base_types.py
rest_filter/encoder/common.py
rest_filter/encoder/encoder.py
rest_filter/translator/__init__.py
rest_filter/translator/mongodb_translator.py
rest_filter/translator/mssql_translator.py
rest_filter/translator/translator.py
rest_filter-1.0.2.dist-info/LICENSE
rest_filter-1.0.2.dist-info/METADATA
rest_filter-1.0.2.dist-info/WHEEL
rest_filter-1.0.2.dist-info/top_level.txt
rest_filter-1.0.2.dist-info/RECORD
