Metadata-Version: 2.1
Name: rest-filter
Version: 1.0.2
Summary: A query string parsing library for REST server queries
Home-page: https://gitlab.com/sagbot/odata_parser
Author: Sagiv Oulu
Author-email: sagiv.oulu@gmail.com
License: MIT
Platform: UNKNOWN
Classifier: Programming Language :: Python :: 3
Classifier: License :: OSI Approved :: MIT License
Classifier: Operating System :: OS Independent
Requires-Python: >=3.6
Requires-Dist: parsimonious (==0.8.1)
Requires-Dist: pydantic (==1.7.3)
